integration_tests/__init__.py
integration_tests/acceptance.py
integration_tests/configured_catalog.json
integration_tests/invalid_config.json
integration_tests/sample_config.json
source_courier/__init__.py
source_courier/manifest.yaml
source_courier/run.py
source_courier/source.py
source_courier/spec.yaml
source_courier/schemas/message_history.json
source_courier/schemas/message_info.json
source_courier/schemas/message_output.json
source_courier/schemas/messages.json
airbyte_source_courier-0.1.0.dist-info/METADATA
airbyte_source_courier-0.1.0.dist-info/WHEEL
airbyte_source_courier-0.1.0.dist-info/entry_points.txt
airbyte_source_courier-0.1.0.dist-info/top_level.txt
airbyte_source_courier-0.1.0.dist-info/RECORD
