Metadata-Version: 2.1
Name: airbyte-source-courier
Version: 0.1.0
Summary: Source implementation for Courier.
Author: Airbyte
Author-email: contact@airbyte.io
Requires-Dist: airbyte-cdk ~=0.1
Provides-Extra: tests
Requires-Dist: requests-mock ~=1.9.3 ; extra == 'tests'
Requires-Dist: pytest ~=6.1 ; extra == 'tests'
Requires-Dist: pytest-mock ~=3.6.1 ; extra == 'tests'
